newgeometry14/__init__.py
newgeometry14/geometry.py
newgeometry14-0.0.1.dist-info/LICENSE
newgeometry14-0.0.1.dist-info/METADATA
newgeometry14-0.0.1.dist-info/WHEEL
newgeometry14-0.0.1.dist-info/top_level.txt
newgeometry14-0.0.1.dist-info/RECORD
