Metadata-Version: 2.1
Name: newgeometry14
Version: 0.0.1
Summary: MyGeometry is a simple Python library for calculating the area and perimeter of basic geometric shapes
Home-page: https://github.com/syahrulcaem/geometry_baru
Author: hanifaslam
Author-email: <aslamhanif141@gmail.com>
License: MIT
Keywords: mal,myanimelist
Classifier: Development Status :: 1 - Planning
License-File: LICENSE
